termipod/__init__.py
termipod/backends.py
termipod/cache.py
termipod/completer.py
termipod/config.py
termipod/database.py
termipod/database_update.py
termipod/debug.py
termipod/httpserver.py
termipod/image.py
termipod/itemlist.py
termipod/keymap.py
termipod/player.py
termipod/rss.py
termipod/termipod.py
termipod/ui.py
termipod/utils.py
termipod/yt.py
termipod-2.1.dist-info/LICENSE.txt
termipod-2.1.dist-info/METADATA
termipod-2.1.dist-info/WHEEL
termipod-2.1.dist-info/entry_points.txt
termipod-2.1.dist-info/top_level.txt
termipod-2.1.dist-info/RECORD
