Metadata-Version: 2.1
Name: termipod
Version: 2.1
Summary: Manage and read podcasts and youtubevideos in your terminal
Home-page: https://github.com/rools32/termipod
Author: Cyril Bordage
Author-email: UNKNOWN
License: UNKNOWN
Keywords: podcast curses terminal rss youtube
Platform: UNKNOWN
Classifier: Development Status :: 5 - Production/Stable
Classifier: Environment :: Console :: Curses
Classifier: Intended Audience :: End Users/Desktop
Classifier: Programming Language :: Python :: 3
Classifier: Topic :: Multimedia :: Sound/Audio
Classifier: License :: OSI Approved :: GNU General Public License v3 (GPLv3)
Requires-Dist: feedparser
Requires-Dist: appdirs
Requires-Dist: youtube-dl
Requires-Dist: python-mpv
